<?xml version="1.0"?>
<ClipboardMungerScriptContainer xmlns:xsi="http://www.w3.org/2001/XMLSchema-instance" xmlns:xsd="http://www.w3.org/2001/XMLSchema">
  <Title>FirstCharacterOnly</Title>
  <Description>Just the first character</Description>
  <Script>// template (CSharp)

using System;

public class Script : Interfaces.IClipboard
{	
	public string Munge (string clipboardSource)
	{
		return clipboardSource.Substring (0,1);
	}
}	
</Script>
  <Language>1</Language>
  <TestData>jhjhgjhjhg</TestData>
  <References />
</ClipboardMungerScriptContainer>